ebookocd/__init__.py
ebookocd/__main__.py
ebookocd/api.py
ebookocd/core.py
ebookocd/transform/__init__.py
ebookocd/transform/default.py
ebookocd/transform/drizzt.py
ebookocd/transform/monty.py
tests/__init__.py
tests/test_drizzt.py
tests/test_init.py
tests/test_main.py
tests/data/drizzt/mimetype
tests/data/drizzt/META-INF/container.xml
tests/data/drizzt/OEBPS/content.opf
tests/data/drizzt/OEBPS/toc.ncx
tests/data/drizzt/OEBPS/Styles/stylesheet.css
tests/data/drizzt/OEBPS/Text/drizzt.xhtml
tests/data/drizzt/OEBPS/Text/first.xhtml
tests/data/drizzt/OEBPS/Text/lorem.xhtml
tests/data/drizzt/OEBPS/Text/monty.xhtml
eBookOCD-0.1.dist-info/LICENSE
eBookOCD-0.1.dist-info/METADATA
eBookOCD-0.1.dist-info/WHEEL
eBookOCD-0.1.dist-info/entry_points.txt
eBookOCD-0.1.dist-info/top_level.txt
eBookOCD-0.1.dist-info/RECORD
