Metadata-Version: 2.1
Name: eBookOCD
Version: 0.1
Summary: Extensible utility to rewrite eBook content. Useful for fixing common mistakes made by authors and publishers alike.
Home-page: https://gitlab.com/ebookocd/ebookocd
Author: Ralph Seichter
Author-email: ebookocd@seichter.de
License: GPLv3+
Platform: UNKNOWN
Classifier: Development Status :: 4 - Beta
Classifier: License :: OSI Approved :: GNU General Public License v3 or later (GPLv3+)
Classifier: Operating System :: OS Independent
Classifier: Programming Language :: Python :: 3.8
Requires-Python: >=3.8
Requires-Dist: defusedxml (>=0.6.0)
